{
    "name": "HTTPS_Processor",
    "type": "http",
    "score_weight": 1,
    "definition": {
        "requests": [
            {
                "host": "{{.Host}}",
                "path": "/metrics/status/processing",
                "https": true,
                "port": 443,
                "method": "GET",
                "matchcode": true,
                "code": 200,
                "headers": {
                    "Host": "{{.Host}}"
                }
            }
        ]
    },
    "attributes": {
        "admin": {
            "Host": "processor.{{.TeamNumber}}.placebo-pharma.com"
        }
    }
}
